agnostic_migrations/__init__.py
agnostic_migrations-1.0.0.dist-info/METADATA
agnostic_migrations-1.0.0.dist-info/WHEEL
agnostic_migrations-1.0.0.dist-info/RECORD
