Metadata-Version: 2.1
Name: agnostic-migrations
Version: 1.0.0
Summary: 
Author: Source Allies
Author-email: pypi@sourceallies.com
Requires-Python: >=3.11,<4.0
Classifier: Programming Language :: Python :: 3
Classifier: Programming Language :: Python :: 3.11
Classifier: Programming Language :: Python :: 3.12
